sshcp/__init__.py
sshcp/__main__.py
sshcp/bookmarks.py
sshcp/cli.py
sshcp/config.py
sshcp/conflict.py
sshcp/selector.py
sshcp/ssh_config.py
sshcp/sync.py
sshcp/transfer.py
sshcp/watch.py
sshcp-0.2.2.dist-info/METADATA
sshcp-0.2.2.dist-info/WHEEL
sshcp-0.2.2.dist-info/entry_points.txt
sshcp-0.2.2.dist-info/RECORD
