Metadata-Version: 2.4
Name: sshcp
Version: 0.2.2
Summary: Easy SSH file copy CLI tool with persistent server selection
Requires-Python: >=3.10
Requires-Dist: rich>=13.0.0
Requires-Dist: simple-term-menu>=1.6.0
Requires-Dist: typer>=0.9.0
Requires-Dist: watchdog>=4.0.0
